LICENSE.txt
README.md
setup.cfg
setup.py
dnull/__init__.py
dnull/gauth.py
dnull/gcal.py
dnull/gconfig.py
dnull/gdrive.py
dnull/gsheets.py
dnull.egg-info/PKG-INFO
dnull.egg-info/SOURCES.txt
dnull.egg-info/dependency_links.txt
dnull.egg-info/requires.txt
dnull.egg-info/top_level.txt