Metadata-Version: 2.1
Name: dnull
Version: 0.0.9
Summary: UES Lib python helpers
Home-page: https://gitlab.com/ues/lib/python/dnull
Author: Bohdan Sukhomlinov
Author-email: shellshock.dnull@gmail.com
License: MIT
Download-URL: https://gitlab.com/ues/lib/python/dnull/-/archive/0.0.9/dnull-0.0.9.tar.gz
Keywords: google,calendar,ues
Platform: UNKNOWN
Classifier: Development Status :: 3 - Alpha
Classifier: Intended Audience :: Developers
Classifier: Topic :: Software Development :: Build Tools
Classifier: License :: OSI Approved :: MIT License
Classifier: Programming Language :: Python :: 3
Classifier: Programming Language :: Python :: 3.8
Classifier: Programming Language :: Python :: 3.9
License-File: LICENSE.txt
